.DS_Store
MANIFEST.in
README.txt
__init__.py
setup.py
Doc/.buildinfo
Doc/fmkf.html
Doc/genindex.html
Doc/index.html
Doc/modules.html
Doc/objects.inv
Doc/py-modindex.html
Doc/search.html
Doc/searchindex.js
Doc/_sources/fmkf.rst.txt
Doc/_sources/index.rst.txt
Doc/_sources/modules.rst.txt
Doc/_static/alabaster.css
Doc/_static/basic.css
Doc/_static/custom.css
Doc/_static/doctools.js
Doc/_static/documentation_options.js
Doc/_static/file.png
Doc/_static/jquery-3.5.1.js
Doc/_static/jquery.js
Doc/_static/language_data.js
Doc/_static/minus.png
Doc/_static/plus.png
Doc/_static/pygments.css
Doc/_static/searchtools.js
Doc/_static/underscore-1.3.1.js
Doc/_static/underscore.js
examples/.DS_Store
examples/__init__.py
examples/create_save_embedding.py
examples/create_test_dataset_embedding.py
examples/face_recognition.py
examples/show_path_face.py
examples/5-celebrity-faces-dataset/data/train/ben_afflek/httpcsvkmeuaeccjpg.jpg
examples/5-celebrity-faces-dataset/data/train/ben_afflek/httpimagesfandangocomrImageRendererredesignstaticimgnoxportraitjpgpcpcpcimagesmasterrepositoryperformerimagespjpg.jpg
examples/5-celebrity-faces-dataset/data/train/ben_afflek/httpssmediacacheakpinimgcomxdbbdbbbececacdecdcdfjpg.jpg
examples/5-celebrity-faces-dataset/data/train/ben_afflek/httpssmediacacheakpinimgcomxdfdfadcfeabjpg.jpg
examples/5-celebrity-faces-dataset/data/train/ben_afflek/httpssmediacacheakpinimgcomxedaedabcbefbcbabbjpg.jpg
examples/5-celebrity-faces-dataset/data/train/ben_afflek/httpssmediacacheakpinimgcomxeebdfdbaaajpg.jpg
examples/5-celebrity-faces-dataset/data/train/ben_afflek/httpssmediacacheakpinimgcomxeeedcacddeccccacfjpg.jpg
examples/5-celebrity-faces-dataset/data/train/ben_afflek/httpsuploadwikimediaorgwikipediacommonsthumbddBenAffleckbyGageSkidmorejpgpxBenAffleckbyGageSkidmorejpg.jpg
examples/5-celebrity-faces-dataset/data/train/ben_afflek/httptrwebimgacstanetcxbdddmediasnmediajpg.jpg
face_mtcnn_keras_facenet.egg-info/PKG-INFO
face_mtcnn_keras_facenet.egg-info/SOURCES.txt
face_mtcnn_keras_facenet.egg-info/dependency_links.txt
face_mtcnn_keras_facenet.egg-info/top_level.txt
