Metadata-Version: 1.0
Name: face-mtcnn-keras-facenet
Version: 1.1
Summary: 人脸识别
Home-page: UNKNOWN
Author: leon.hu
Author-email: sdcxhuoxiaoqi@126.com
License: MIT
Platform: Linux
